<?xml version="1.0" encoding="UTF-8"?>
<questestinterop xmlns="http://www.imsglobal.org/xsd/ims_qtiasiv1p2" xmlns:xsi="http://www.w3.org/2001/XMLSchema-instance" xsi:schemaLocation="http://www.imsglobal.org/xsd/ims_qtiasiv1p2 http://www.imsglobal.org/xsd/ims_qtiasiv1p2p1.xsd">
  <assessment ident="g5448c809c4c3ad45ea229aac21fd65ad" title="Unit Assessment - Vocabulary Activity 01">
    <qtimetadata>
      <qtimetadatafield>
        <fieldlabel>cc_maxattempts</fieldlabel>
        <fieldentry>1</fieldentry>
      </qtimetadatafield>
      <qtimetadatafield>
              <fieldlabel>ACTFL_Communication</fieldlabel>
              <fieldentry>Interpretive</fieldentry>
            </qtimetadatafield>
            <qtimetadatafield>
              <fieldlabel>ACTFL_Cultures</fieldlabel>
              <fieldentry>Products</fieldentry>
            </qtimetadatafield>
            <qtimetadatafield>
              <fieldlabel>FL_Benchmark_Code1</fieldlabel>
              <fieldentry>WL.K12.IM.2.1</fieldentry>
            </qtimetadatafield>
            <qtimetadatafield>
              <fieldlabel>FL_Benchmark_Code2</fieldlabel>
              <fieldentry>ELA.K12.EE.2.1</fieldentry>
            </qtimetadatafield>
             <qtimetadatafield>
              <fieldlabel>FL_Benchmark_Code3</fieldlabel>
              <fieldentry>ELA.K12.EE.3.1</fieldentry>
            </qtimetadatafield>
             <qtimetadatafield>
              <fieldlabel>FL_Benchmark_Code4</fieldlabel>
              <fieldentry>MA.K12.MTR.5.1</fieldentry>
            </qtimetadatafield>
    </qtimetadata>
    <section ident="root_section">
      <item ident="g02ae1d7933b89c63318f28fcda85c7b0" title="Choice true and false">
        <itemmetadata>
          <qtimetadata>
            <qtimetadatafield>
              <fieldlabel>question_type</fieldlabel>
              <fieldentry>multiple_dropdowns_question</fieldentry>
            </qtimetadatafield>
            <qtimetadatafield>
              <fieldlabel>points_possible</fieldlabel>
              <fieldentry>5.0</fieldentry>
            </qtimetadatafield>
            <qtimetadatafield>
              <fieldlabel>original_answer_ids</fieldlabel>
              <fieldentry>44920,20685,46400,42403,26437,94899,16625,91895,6542,92645</fieldentry>
            </qtimetadatafield>
            <qtimetadatafield>
              <fieldlabel>assessment_question_identifierref</fieldlabel>
              <fieldentry>g9cb75111c78e01e8756bb1232b94a147</fieldentry>
            </qtimetadatafield>
          </qtimetadata>
        </itemmetadata>
        <presentation>
          <material>
            <mattext texttype="text/html">&lt;div&gt;&lt;div class="prompt"&gt;
&lt;p&gt;Patrimoine de la ville is offering a guided tour of Paris. Read the description of the tour, then read each statement and indicate whether it is true &lt;strong&gt;&lt;i&gt;(vrai)&lt;/i&gt;&lt;/strong&gt; or false &lt;strong&gt;&lt;i&gt;(faux)&lt;/i&gt;&lt;/strong&gt;.&lt;/p&gt;
&lt;/div&gt;
&lt;div&gt;
&lt;p&gt;&lt;img src="https://cdn.waysidepublishing.com/textbooks/QTI/ECF2/ecf2_u4_ua_vq_activity1_ex.jpg" alt="Some people cycling in Paris"&gt;&lt;/p&gt;
&lt;p&gt;L’association « Patrimoine de la ville » vous invite à une visite guidée à vélo ou à roller. Vous allez visiter quelques quartiers de Paris. Notre guide bénévole va parler de l’histoire des bâtiments, il va donner des anecdotes sur, par exemple, la plus ancienne maison de Paris, et également vous expliquer l’origine des noms des rues. Vous allez pédaler dans la plus longue rue de la ville mais aussi dans la plus petite. Si vous êtes curieux et que vous aimez l’histoire, prenez votre vélo ou vos rollers et venez avec nous ! Nous avons aussi cinq vélos à louer. Réservez à l’avance. N’oubliez pas de prendre une bouteille d’eau ! Rendez-vous dimanche 22 août à 14h devant les Galeries Lafayettes, 60 avenue des Champs Élysées, Paris. Si à votre tour, vous voulez aussi faire découvrir des endroits intéressants, devenez guide historique, appelez le 06.21.53.64.77&lt;/p&gt;
&lt;p&gt;1. C’est une invitation à une visite guidée.&lt;/p&gt;
[RESPONSE1]&lt;br&gt;&lt;br&gt;
&lt;p&gt;2. Il faut réserver les billets à l’avance.&lt;/p&gt;
[RESPONSE2]&lt;br&gt;&lt;br&gt;
&lt;p&gt;3. On peut faire du roller pendant la visite.&lt;/p&gt;
[RESPONSE3]&lt;br&gt;&lt;br&gt;
&lt;p&gt;4. Le départ se trouve dans les galeries Lafayette.&lt;/p&gt;
[RESPONSE4]&lt;br&gt;&lt;br&gt;
&lt;p&gt;5. Si on veut, on peut aussi devenir guides bénévoles.&lt;/p&gt;
[RESPONSE5]&lt;/div&gt;&lt;/div&gt;</mattext>
          </material>
          <response_lid ident="response_RESPONSE1">
            <material>
              <mattext>RESPONSE1</mattext>
            </material>
            <render_choice>
              <response_label ident="44920">
                <material>
                  <mattext texttype="text/plain">vrai</mattext>
                </material>
              </response_label>
              <response_label ident="20685">
                <material>
                  <mattext texttype="text/plain">faux</mattext>
                </material>
              </response_label>
            </render_choice>
          </response_lid>
          <response_lid ident="response_RESPONSE2">
            <material>
              <mattext>RESPONSE2</mattext>
            </material>
            <render_choice>
              <response_label ident="46400">
                <material>
                  <mattext texttype="text/plain">vrai</mattext>
                </material>
              </response_label>
              <response_label ident="42403">
                <material>
                  <mattext texttype="text/plain">faux</mattext>
                </material>
              </response_label>
            </render_choice>
          </response_lid>
          <response_lid ident="response_RESPONSE3">
            <material>
              <mattext>RESPONSE3</mattext>
            </material>
            <render_choice>
              <response_label ident="26437">
                <material>
                  <mattext texttype="text/plain">vrai</mattext>
                </material>
              </response_label>
              <response_label ident="94899">
                <material>
                  <mattext texttype="text/plain">faux</mattext>
                </material>
              </response_label>
            </render_choice>
          </response_lid>
          <response_lid ident="response_RESPONSE4">
            <material>
              <mattext>RESPONSE4</mattext>
            </material>
            <render_choice>
              <response_label ident="16625">
                <material>
                  <mattext texttype="text/plain">vrai</mattext>
                </material>
              </response_label>
              <response_label ident="91895">
                <material>
                  <mattext texttype="text/plain">faux</mattext>
                </material>
              </response_label>
            </render_choice>
          </response_lid>
          <response_lid ident="response_RESPONSE5">
            <material>
              <mattext>RESPONSE5</mattext>
            </material>
            <render_choice>
              <response_label ident="6542">
                <material>
                  <mattext texttype="text/plain">vrai</mattext>
                </material>
              </response_label>
              <response_label ident="92645">
                <material>
                  <mattext texttype="text/plain">faux</mattext>
                </material>
              </response_label>
            </render_choice>
          </response_lid>
        </presentation>
        <resprocessing>
          <outcomes>
            <decvar maxvalue="100" minvalue="0" varname="SCORE" vartype="Decimal"/>
          </outcomes>
          <respcondition>
            <conditionvar>
              <varequal respident="response_RESPONSE1">44920</varequal>
            </conditionvar>
            <setvar varname="SCORE" action="Add">20.00</setvar>
          </respcondition>
          <respcondition>
            <conditionvar>
              <varequal respident="response_RESPONSE2">42403</varequal>
            </conditionvar>
            <setvar varname="SCORE" action="Add">20.00</setvar>
          </respcondition>
          <respcondition>
            <conditionvar>
              <varequal respident="response_RESPONSE3">26437</varequal>
            </conditionvar>
            <setvar varname="SCORE" action="Add">20.00</setvar>
          </respcondition>
          <respcondition>
            <conditionvar>
              <varequal respident="response_RESPONSE4">91895</varequal>
            </conditionvar>
            <setvar varname="SCORE" action="Add">20.00</setvar>
          </respcondition>
          <respcondition>
            <conditionvar>
              <varequal respident="response_RESPONSE5">6542</varequal>
            </conditionvar>
            <setvar varname="SCORE" action="Add">20.00</setvar>
          </respcondition>
        </resprocessing>
      </item>
    </section>
  </assessment>
</questestinterop>
