<?xml version="1.0" encoding="UTF-8"?>
<questestinterop xmlns="http://www.imsglobal.org/xsd/ims_qtiasiv1p2" xmlns:xsi="http://www.w3.org/2001/XMLSchema-instance" xsi:schemaLocation="http://www.imsglobal.org/xsd/ims_qtiasiv1p2 http://www.imsglobal.org/xsd/ims_qtiasiv1p2p1.xsd">
  <assessment ident="g12cd9553ad18608b1ecb54bd7bb81c56" title="Communiquons 2 - Grammar Activity 01">
    <qtimetadata>
      <qtimetadatafield>
        <fieldlabel>cc_maxattempts</fieldlabel>
        <fieldentry>1</fieldentry>
      </qtimetadatafield>
      <qtimetadatafield>
              <fieldlabel>ACTFL_Communication</fieldlabel>
              <fieldentry>Interpretive</fieldentry>
            </qtimetadatafield>
            <qtimetadatafield>
              <fieldlabel>FL_Benchmark_Code1</fieldlabel>
              <fieldentry>WL.K12.IM.2.1</fieldentry>
            </qtimetadatafield>
             <qtimetadatafield>
              <fieldlabel>FL_Benchmark_Code2</fieldlabel>
              <fieldentry>ELA.K12.EE.2.1</fieldentry>
            </qtimetadatafield>
             <qtimetadatafield>
              <fieldlabel>FL_Benchmark_Code3</fieldlabel>
              <fieldentry>ELA.K12.EE.3.1</fieldentry>
            </qtimetadatafield>
             <qtimetadatafield>
              <fieldlabel>FL_Benchmark_Code4</fieldlabel>
              <fieldentry>MA.K12.MTR.5.1</fieldentry>
            </qtimetadatafield>
            <qtimetadatafield>
              <fieldlabel>FL_Benchmark_Code5</fieldlabel>
              <fieldentry>MA.K12.MTR.6.1</fieldentry>
            </qtimetadatafield>
    </qtimetadata>
    <section ident="root_section">
      <item ident="g6be37ef8bcdf7a5b91f02b4bdc4c2c7d" title="simple-choice">
        <itemmetadata>
          <qtimetadata>
            <qtimetadatafield>
              <fieldlabel>question_type</fieldlabel>
              <fieldentry>multiple_choice_question</fieldentry>
            </qtimetadatafield>
            <qtimetadatafield>
              <fieldlabel>points_possible</fieldlabel>
              <fieldentry>1</fieldentry>
            </qtimetadatafield>
            <qtimetadatafield>
              <fieldlabel>original_answer_ids</fieldlabel>
              <fieldentry>31391,39694,25985</fieldentry>
            </qtimetadatafield>
            <qtimetadatafield>
              <fieldlabel>assessment_question_identifierref</fieldlabel>
              <fieldentry>g0130eb45c3205845e082a8a20fa5691f</fieldentry>
            </qtimetadatafield>
          </qtimetadata>
        </itemmetadata>
        <presentation>
          <material>
            <mattext texttype="text/html">&lt;div&gt;&lt;p&gt;Read each sentence and select the response that is equivalent to the original sentence.&lt;/p&gt;
    
           &lt;p&gt;1. Tu trouveras ton passeport et ton portefeuille dans la poche de ta valise.&lt;/p&gt;&lt;/div&gt;</mattext>
          </material>
          <response_lid ident="response1" rcardinality="Single">
            <render_choice>
              <response_label ident="31391">
                <material>
                  <mattext texttype="text/plain">Tu le trouveras dans la poche de ta valise.</mattext>
                </material>
              </response_label>
              <response_label ident="39694">
                <material>
                  <mattext texttype="text/plain">Tu la trouveras dans la poche de ta valise.</mattext>
                </material>
              </response_label>
              <response_label ident="25985">
                <material>
                  <mattext texttype="text/plain">Tu les trouveras dans la poche de ta valise.</mattext>
                </material>
              </response_label>
            </render_choice>
          </response_lid>
        </presentation>
        <resprocessing>
          <outcomes>
            <decvar maxvalue="100" minvalue="0" varname="SCORE" vartype="Decimal"/>
          </outcomes>
          <respcondition continue="No">
            <conditionvar>
              <varequal respident="response1">25985</varequal>
            </conditionvar>
            <setvar action="Set" varname="SCORE">100</setvar>
          </respcondition>
        </resprocessing>
      </item>
      <item ident="gb1099c65f998548d8ebad1128d3d47d4" title="simple-choice">
        <itemmetadata>
          <qtimetadata>
            <qtimetadatafield>
              <fieldlabel>question_type</fieldlabel>
              <fieldentry>multiple_choice_question</fieldentry>
            </qtimetadatafield>
            <qtimetadatafield>
              <fieldlabel>points_possible</fieldlabel>
              <fieldentry>1</fieldentry>
            </qtimetadatafield>
            <qtimetadatafield>
              <fieldlabel>original_answer_ids</fieldlabel>
              <fieldentry>83711,18390,74356</fieldentry>
            </qtimetadatafield>
            <qtimetadatafield>
              <fieldlabel>assessment_question_identifierref</fieldlabel>
              <fieldentry>gafeccaa5fa0de40e2a0223d69447c3a3</fieldentry>
            </qtimetadatafield>
          </qtimetadata>
        </itemmetadata>
        <presentation>
          <material>
            <mattext texttype="text/html">&lt;div&gt;2. Benoît mettra son écharpe quand il aura froid.&lt;/div&gt;</mattext>
          </material>
          <response_lid ident="response1" rcardinality="Single">
            <render_choice>
              <response_label ident="83711">
                <material>
                  <mattext texttype="text/plain">Benoît les mettra quand il aura froid.</mattext>
                </material>
              </response_label>
              <response_label ident="18390">
                <material>
                  <mattext texttype="text/plain">Benoît la mettra quand il aura froid.</mattext>
                </material>
              </response_label>
              <response_label ident="74356">
                <material>
                  <mattext texttype="text/plain">Benoît le mettra quand il aura froid.</mattext>
                </material>
              </response_label>
            </render_choice>
          </response_lid>
        </presentation>
        <resprocessing>
          <outcomes>
            <decvar maxvalue="100" minvalue="0" varname="SCORE" vartype="Decimal"/>
          </outcomes>
          <respcondition continue="No">
            <conditionvar>
              <varequal respident="response1">18390</varequal>
            </conditionvar>
            <setvar action="Set" varname="SCORE">100</setvar>
          </respcondition>
        </resprocessing>
      </item>
      <item ident="g845f1c7a151a4fdfaed07b50a65b0400" title="simple-choice">
        <itemmetadata>
          <qtimetadata>
            <qtimetadatafield>
              <fieldlabel>question_type</fieldlabel>
              <fieldentry>multiple_choice_question</fieldentry>
            </qtimetadatafield>
            <qtimetadatafield>
              <fieldlabel>points_possible</fieldlabel>
              <fieldentry>1</fieldentry>
            </qtimetadatafield>
            <qtimetadatafield>
              <fieldlabel>original_answer_ids</fieldlabel>
              <fieldentry>59614,88087,64715</fieldentry>
            </qtimetadatafield>
            <qtimetadatafield>
              <fieldlabel>assessment_question_identifierref</fieldlabel>
              <fieldentry>g287abb2822b88be40ef5e6ba5c9597cd</fieldentry>
            </qtimetadatafield>
          </qtimetadata>
        </itemmetadata>
        <presentation>
          <material>
            <mattext texttype="text/html">&lt;div&gt;3. Antoine prendra le métro à 7h10.&lt;/div&gt;</mattext>
          </material>
          <response_lid ident="response1" rcardinality="Single">
            <render_choice>
              <response_label ident="59614">
                <material>
                  <mattext texttype="text/plain">Antoine le prendra à 7h10.</mattext>
                </material>
              </response_label>
              <response_label ident="88087">
                <material>
                  <mattext texttype="text/plain">Antoine la prendra à 7h10.</mattext>
                </material>
              </response_label>
              <response_label ident="64715">
                <material>
                  <mattext texttype="text/plain">Antoine les prendra à 7h10.</mattext>
                </material>
              </response_label>
            </render_choice>
          </response_lid>
        </presentation>
        <resprocessing>
          <outcomes>
            <decvar maxvalue="100" minvalue="0" varname="SCORE" vartype="Decimal"/>
          </outcomes>
          <respcondition continue="No">
            <conditionvar>
              <varequal respident="response1">59614</varequal>
            </conditionvar>
            <setvar action="Set" varname="SCORE">100</setvar>
          </respcondition>
        </resprocessing>
      </item>
    </section>
  </assessment>
</questestinterop>
